commit_agent/__init__ copy.py
commit_agent/__init__.py
commit_agent/git_utils/__init__.py
commit_agent/git_utils/git_local.py
commit_agent/main.py
commit_agent-0.1.0.dist-info/METADATA
commit_agent-0.1.0.dist-info/WHEEL
commit_agent-0.1.0.dist-info/entry_points.txt
commit_agent-0.1.0.dist-info/RECORD
